pwbus_http/__init__.py
pwbus_http/server.py
pwbus_web/__init__.py
pwbus_web/http_server.py
pwbus_web/cli/http_server.py
pwbus_web/client/client.py
pwbus_web/client/pwbus_bottle_client.py
pwbus_web/http/server.py
pwbus_http-0.1.33.dist-info/LICENSE.txt
pwbus_http-0.1.33.dist-info/METADATA
pwbus_http-0.1.33.dist-info/WHEEL
pwbus_http-0.1.33.dist-info/entry_points.txt
pwbus_http-0.1.33.dist-info/top_level.txt
pwbus_http-0.1.33.dist-info/RECORD
