Metadata-Version: 2.1
Name: pwbus-http
Version: 0.1.33
Summary: HTTP Server for PWBUS
Home-page: https://github.com/fszostak/pwbus-http
Author: Fabio Szostak
Author-email: fszostak@gmail.com
License: UNKNOWN
Platform: UNKNOWN
Classifier: Development Status :: 4 - Beta
Classifier: Programming Language :: Python :: 3.7
Classifier: Programming Language :: Python :: 3.8
Classifier: License :: OSI Approved :: MIT License
Classifier: Operating System :: OS Independent
Requires-Python: >=3.7
Requires-Dist: Click (==7.1.2)
Requires-Dist: Flask-Cors (==3.0.8)
Requires-Dist: Flask (==1.1.2)
Requires-Dist: Jinja2 (==2.11.3)
Requires-Dist: MarkupSafe (==1.1.1)
Requires-Dist: Werkzeug (==1.0.1)
Requires-Dist: itsdangerous (==1.1.0)
Requires-Dist: pwbus (==0.1.38)
Requires-Dist: requests (==2.25.1)
Requires-Dist: six (==1.15.0)
Requires-Dist: uWSGI (==2.0.19.1)
Requires-Dist: urllib3 (==1.26.4)
